{
  "date": "2023-07-12",
  "exchange-rates": {
    "cad": 0.00102,
    "aud": 0.001149,
    "cop": 3.234637,
    "bdt": 0.083916,
    "clp": 0.630139,
    "czk": 0.016714,
    "aed": 0.002836,
    "brl": 0.003748,
    "ars": 0.203287,
    "chf": 0.000678,
    "cny": 0.005568,
    "bgn": 0.001371,
    "dkk": 0.00522,
    "eur": 0.0007,
    "huf": 0.265243,
    "ils": 0.002847,
    "inr": 0.063594,
    "hrk": 0.005387,
    "jpy": 0.107693,
    "egp": 0.023886,
    "gbp": 0.000596,
    "hkd": 0.006046,
    "krw": 1,
    "idr": 11.686975,
    "myr": 0.003594,
    "nzd": 0.001241,
    "pkr": 0.211937,
    "mxn": 0.013167,
    "rub": 0.069504,
    "sek": 0.008214,
    "pln": 0.003109,
    "thb": 0.026794,
    "nok": 0.007965,
    "ron": 0.003467,
    "sar": 0.002897,
    "sgd": 0.001034,
    "try": 0.020167,
    "twd": 0.024172,
    "php": 0.042539,
    "uah": 0.02849,
    "npr": 0.101709,
    "omr": 0.000297,
    "vnd": 18.30271,
    "pab": 0.000771,
    "lkr": 0.241504,
    "usd": 0.000772,
    "mad": 0.007514,
    "zar": 0.014237,
    "kes": 0.109049,
    "kwd": 0.000237,
    "ghs": 0.008774,
    "dzd": 0.104572,
    "gel": 0.002004,
    "jod": 0.000548,
    "isk": 0.102889
  }
}