{
  "date": "2023-07-13",
  "exchange-rates": {
    "bgn": 0.013015,
    "chf": 0.006425,
    "cad": 0.009778,
    "bdt": 0.797941,
    "cop": 30.686463,
    "czk": 0.158316,
    "cny": 0.053123,
    "clp": 6.016323,
    "brl": 0.035727,
    "aud": 0.010912,
    "aed": 0.027228,
    "ars": 1.956833,
    "dkk": 0.049587,
    "egp": 0.229252,
    "gbp": 0.005703,
    "huf": 2.49813,
    "eur": 0.006654,
    "ils": 0.027038,
    "hkd": 0.058004,
    "jpy": 1.027692,
    "hrk": 0.050141,
    "idr": 110.977195,
    "inr": 0.607919,
    "krw": 9.47347,
    "mxn": 0.125262,
    "myr": 0.034238,
    "pkr": 2.033322,
    "pln": 0.029533,
    "nzd": 0.011743,
    "nok": 0.074977,
    "ron": 0.032919,
    "rub": 0.670896,
    "sek": 0.076869,
    "sgd": 0.009857,
    "sar": 0.02781,
    "thb": 0.256573,
    "try": 0.193739,
    "uah": 0.270919,
    "zar": 0.134435,
    "twd": 0.230668,
    "vnd": 175.175842,
    "usd": 0.007413,
    "pab": 0.007336,
    "omr": 0.002857,
    "php": 0.40445,
    "npr": 0.965547,
    "mad": 0.071797,
    "lkr": 2.318235,
    "kwd": 0.002273,
    "ghs": 0.083445,
    "kes": 1.047507,
    "jod": 0.005259,
    "isk": 0.977819,
    "gel": 0.019123,
    "dzd": 1
  }
}