{
  "date": "2023-07-29",
  "exchange-rates": {
    "ars": 0.953216,
    "aed": 0.012874,
    "chf": 0.00305,
    "aud": 0.005271,
    "bdt": 0.378873,
    "czk": 0.076303,
    "brl": 0.01656,
    "bgn": 0.006211,
    "cop": 13.811554,
    "cny": 0.025055,
    "cad": 0.004644,
    "clp": 2.898775,
    "dkk": 0.023708,
    "egp": 0.107882,
    "gbp": 0.002728,
    "eur": 0.003177,
    "idr": 52.951358,
    "hrk": 0.023567,
    "huf": 1.222956,
    "ils": 0.012979,
    "krw": 4.463162,
    "jpy": 0.494709,
    "hkd": 0.027338,
    "inr": 0.288318,
    "mxn": 0.058497,
    "nok": 0.035742,
    "nzd": 0.005686,
    "pkr": 1,
    "pln": 0.014039,
    "sar": 0.013148,
    "myr": 0.01596,
    "sgd": 0.004665,
    "sek": 0.036965,
    "ron": 0.015692,
    "rub": 0.322669,
    "thb": 0.118903,
    "twd": 0.10981,
    "try": 0.094357,
    "zar": 0.060536,
    "vnd": 83.050301,
    "usd": 0.003505,
    "pab": 0.003491,
    "npr": 0.459297,
    "uah": 0.128939,
    "omr": 0.00135,
    "php": 0.192483,
    "mad": 0.034001,
    "lkr": 1.152244,
    "kes": 0.496473,
    "kwd": 0.001076,
    "jod": 0.002482,
    "isk": 0.46101,
    "ghs": 0.039767,
    "dzd": 0.475867,
    "gel": 0.009079
  }
}