{
  "date": "2023-07-27",
  "exchange-rates": {
    "bgn": 0.262599,
    "brl": 0.705305,
    "chf": 0.128052,
    "aed": 0.546764,
    "cop": 587.894039,
    "cad": 0.196256,
    "clp": 122.774419,
    "bdt": 16.149702,
    "aud": 0.219648,
    "ars": 40.561486,
    "czk": 3.226779,
    "cny": 1.064527,
    "dkk": 1,
    "egp": 4.599406,
    "eur": 0.13419,
    "hkd": 1.161019,
    "idr": 2236.986249,
    "huf": 51.245251,
    "krw": 189.275948,
    "gbp": 0.114944,
    "inr": 12.201373,
    "jpy": 20.869453,
    "hrk": 1.000944,
    "ils": 0.549567,
    "mxn": 2.507932,
    "nzd": 0.238672,
    "pkr": 42.667439,
    "myr": 0.674412,
    "nok": 1.502143,
    "rub": 13.397828,
    "sek": 1.545781,
    "sar": 0.558343,
    "ron": 0.661002,
    "pln": 0.593491,
    "thb": 5.073822,
    "sgd": 0.197134,
    "try": 4.007389,
    "vnd": 3524.366104,
    "usd": 0.148865,
    "twd": 4.645539,
    "zar": 2.621656,
    "php": 8.115569,
    "omr": 0.057316,
    "mad": 1.446343,
    "uah": 5.495332,
    "lkr": 49.1802,
    "pab": 0.148797,
    "npr": 19.522416,
    "kwd": 0.04569,
    "kes": 21.159624,
    "isk": 19.55038,
    "dzd": 20.110586,
    "jod": 0.105545,
    "ghs": 1.684402,
    "gel": 0.38631
  }
}