{
  "date": "2023-07-04",
  "exchange-rates": {
    "bgn": 0.001376,
    "bdt": 0.082941,
    "aed": 0.002819,
    "cny": 0.005558,
    "cop": 3.203335,
    "brl": 0.003691,
    "ars": 0.198008,
    "czk": 0.016699,
    "aud": 0.00115,
    "cad": 0.001017,
    "clp": 0.613571,
    "chf": 0.000688,
    "egp": 0.023724,
    "dkk": 0.005239,
    "ils": 0.002839,
    "hrk": 0.005355,
    "jpy": 0.110938,
    "huf": 0.263549,
    "hkd": 0.006013,
    "gbp": 0.000605,
    "eur": 0.000703,
    "krw": 1,
    "idr": 11.542636,
    "inr": 0.062882,
    "myr": 0.003581,
    "mxn": 0.013092,
    "nzd": 0.001247,
    "sek": 0.008319,
    "pln": 0.003119,
    "ron": 0.003485,
    "thb": 0.026898,
    "sar": 0.002879,
    "pkr": 0.21957,
    "rub": 0.068707,
    "nok": 0.008211,
    "sgd": 0.001037,
    "try": 0.019932,
    "twd": 0.023892,
    "omr": 0.000296,
    "php": 0.042435,
    "usd": 0.000768,
    "zar": 0.014404,
    "lkr": 0.236058,
    "npr": 0.100475,
    "mad": 0.007542,
    "pab": 0.000766,
    "vnd": 18.20059,
    "uah": 0.028306,
    "kwd": 0.000236,
    "kes": 0.108005,
    "jod": 0.000545,
    "ghs": 0.00877,
    "gel": 0.002,
    "dzd": 0.104096,
    "isk": 0.104751
  }
}