{
  "date": "2023-07-04",
  "exchange-rates": {
    "cad": 5.6e-05,
    "ars": 0.010879,
    "bgn": 7.6e-05,
    "aud": 6.3e-05,
    "aed": 0.000155,
    "clp": 0.033712,
    "brl": 0.000203,
    "cop": 0.176002,
    "czk": 0.000917,
    "cny": 0.000305,
    "bdt": 0.004557,
    "chf": 3.8e-05,
    "egp": 0.001304,
    "dkk": 0.000288,
    "eur": 3.9e-05,
    "gbp": 3.3e-05,
    "hrk": 0.000294,
    "hkd": 0.00033,
    "ils": 0.000156,
    "idr": 0.63419,
    "inr": 0.003455,
    "krw": 0.054943,
    "jpy": 0.006095,
    "huf": 0.01448,
    "mxn": 0.000719,
    "nok": 0.000451,
    "myr": 0.000197,
    "nzd": 6.9e-05,
    "pkr": 0.012064,
    "sgd": 5.7e-05,
    "rub": 0.003775,
    "ron": 0.000191,
    "pln": 0.000171,
    "thb": 0.001478,
    "sar": 0.000158,
    "sek": 0.000457,
    "twd": 0.001313,
    "try": 0.001095,
    "uah": 0.001555,
    "vnd": 1,
    "php": 0.002332,
    "usd": 4.2e-05,
    "zar": 0.000791,
    "omr": 1.6e-05,
    "mad": 0.000414,
    "lkr": 0.01297,
    "npr": 0.00552,
    "pab": 4.2e-05,
    "kes": 0.005934,
    "jod": 3e-05,
    "isk": 0.005755,
    "dzd": 0.005719,
    "gel": 0.00011,
    "kwd": 1.3e-05,
    "ghs": 0.000482
  }
}