{
  "date": "2023-07-02",
  "exchange-rates": {
    "bgn": 1.353331,
    "bdt": 81.677576,
    "czk": 16.439998,
    "ars": 193.616439,
    "aud": 1.133102,
    "aed": 2.773036,
    "chf": 0.675504,
    "cad": 1,
    "clp": 605.088693,
    "cop": 3146.728418,
    "cny": 5.476352,
    "brl": 3.616174,
    "dkk": 5.152277,
    "egp": 23.304058,
    "eur": 0.691594,
    "hkd": 5.916461,
    "gbp": 0.594163,
    "huf": 257.977247,
    "inr": 61.980471,
    "krw": 993.774123,
    "ils": 2.800468,
    "jpy": 108.946442,
    "idr": 11355.023854,
    "hrk": 5.266778,
    "myr": 3.523841,
    "mxn": 12.928391,
    "nzd": 1.235622,
    "sar": 2.831759,
    "ron": 3.431382,
    "rub": 67.061281,
    "thb": 26.628185,
    "sgd": 1.020878,
    "sek": 8.14405,
    "pkr": 216.302626,
    "pln": 3.068269,
    "nok": 8.162952,
    "try": 19.667886,
    "twd": 23.52595,
    "php": 41.73042,
    "uah": 27.884603,
    "vnd": 17806.043604,
    "pab": 0.755001,
    "lkr": 232.557382,
    "usd": 0.754973,
    "omr": 0.290673,
    "mad": 7.471999,
    "npr": 99.076279,
    "zar": 14.220491,
    "kwd": 0.23214,
    "jod": 0.535656,
    "kes": 106.152108,
    "dzd": 102.532186,
    "isk": 102.880493,
    "ghs": 8.644738,
    "gel": 1.970775
  }
}