{
  "date": "2023-08-06",
  "exchange-rates": {
    "aed": 0.380164,
    "cad": 0.138521,
    "bgn": 0.183893,
    "cny": 0.742135,
    "ars": 28.567063,
    "clp": 87.445442,
    "bdt": 11.197259,
    "chf": 0.090316,
    "brl": 0.504403,
    "aud": 0.157177,
    "czk": 2.281529,
    "gbp": 0.08119,
    "dkk": 0.7005,
    "egp": 3.179537,
    "hkd": 0.808401,
    "hrk": 0.695927,
    "idr": 1568.343317,
    "ils": 0.378061,
    "huf": 36.639461,
    "myr": 0.471452,
    "krw": 134.969743,
    "mxn": 1.767646,
    "nok": 1.055496,
    "jpy": 14.671817,
    "nzd": 0.171569,
    "pkr": 29.119257,
    "ron": 0.46499,
    "pln": 0.416915,
    "cop": 428.516459,
    "rub": 9.923181,
    "sar": 0.388241,
    "sek": 1.095757,
    "sgd": 0.138599,
    "thb": 3.58946,
    "try": 2.788395,
    "twd": 3.277521,
    "uah": 3.794302,
    "eur": 0.09388,
    "usd": 0.103501,
    "inr": 8.557867,
    "php": 5.748302,
    "pab": 0.102736,
    "vnd": 2456.600956,
    "npr": 13.609237,
    "omr": 0.039852,
    "kwd": 0.03183,
    "kes": 14.608345,
    "mad": 1,
    "jod": 0.07329,
    "zar": 1.91156,
    "lkr": 32.977895,
    "isk": 13.639428,
    "ghs": 1.160839,
    "gel": 0.269625,
    "dzd": 14.02866
  }
}