{
  "date": "2023-08-06",
  "exchange-rates": {
    "brl": 0.26387,
    "chf": 0.047247,
    "bdt": 5.857657,
    "cny": 0.388235,
    "ars": 14.944375,
    "clp": 45.745602,
    "cop": 224.171128,
    "cad": 0.072465,
    "aed": 0.198876,
    "aud": 0.082225,
    "czk": 1.193543,
    "bgn": 0.0962,
    "eur": 0.049112,
    "krw": 70.607135,
    "ils": 0.197776,
    "huf": 19.167313,
    "jpy": 7.675312,
    "gbp": 0.042473,
    "egp": 1.663321,
    "inr": 4.476903,
    "hkd": 0.422901,
    "hrk": 0.364063,
    "idr": 820.452243,
    "dkk": 0.366455,
    "myr": 0.246632,
    "mxn": 0.924714,
    "pln": 0.218102,
    "ron": 0.243252,
    "nok": 0.552165,
    "rub": 5.191144,
    "sgd": 0.072506,
    "sek": 0.573227,
    "sar": 0.203101,
    "pkr": 15.233246,
    "nzd": 0.089753,
    "thb": 1.877765,
    "twd": 1.71458,
    "uah": 1.984925,
    "vnd": 1285.129183,
    "php": 3.007127,
    "try": 1.458702,
    "pab": 0.053745,
    "omr": 0.020848,
    "usd": 0.054145,
    "zar": 1,
    "npr": 7.119442,
    "mad": 0.523133,
    "lkr": 17.251827,
    "kwd": 0.016651,
    "ghs": 0.607273,
    "dzd": 7.338856,
    "kes": 7.642108,
    "gel": 0.14105,
    "isk": 7.135236,
    "jod": 0.03834
  }
}