{
  "date": "2023-07-21",
  "exchange-rates": {
    "aed": 0.170601,
    "bgn": 0.081596,
    "cny": 0.333352,
    "brl": 0.222871,
    "cad": 0.061201,
    "chf": 0.040255,
    "ars": 12.477445,
    "aud": 0.068677,
    "bdt": 5.071374,
    "czk": 1,
    "clp": 37.946324,
    "cop": 184.808481,
    "dkk": 0.310807,
    "hkd": 0.362921,
    "huf": 15.915124,
    "gbp": 0.036088,
    "hrk": 0.312296,
    "idr": 697.841284,
    "jpy": 6.505702,
    "ils": 0.167794,
    "inr": 3.812726,
    "eur": 0.041715,
    "egp": 1.430547,
    "krw": 59.567179,
    "pkr": 13.292654,
    "nzd": 0.074706,
    "mxn": 0.784787,
    "nok": 0.466265,
    "pln": 0.185709,
    "myr": 0.211585,
    "ron": 0.205649,
    "rub": 4.184608,
    "sgd": 0.061669,
    "sar": 0.174233,
    "sek": 0.480511,
    "thb": 1.593191,
    "usd": 0.046446,
    "php": 2.539503,
    "pab": 0.046723,
    "try": 1.247097,
    "uah": 1.725563,
    "twd": 1.448385,
    "omr": 0.017883,
    "vnd": 1098.609553,
    "mad": 0.454537,
    "lkr": 15.244147,
    "npr": 6.133731,
    "zar": 0.833147,
    "kwd": 0.014254,
    "jod": 0.032935,
    "gel": 0.119136,
    "ghs": 0.542209,
    "isk": 6.102534,
    "dzd": 6.261659,
    "kes": 6.586988
  }
}