{
  "date": "2023-07-21",
  "exchange-rates": {
    "aud": 0.142924,
    "chf": 0.083775,
    "brl": 0.46382,
    "cop": 384.607938,
    "bgn": 0.169811,
    "aed": 0.35504,
    "czk": 2.081116,
    "ars": 25.967015,
    "cad": 0.127367,
    "clp": 78.970712,
    "bdt": 10.554119,
    "cny": 0.693744,
    "dkk": 0.646825,
    "gbp": 0.075104,
    "idr": 1452.288853,
    "ils": 0.349199,
    "jpy": 13.539122,
    "inr": 7.934725,
    "hkd": 0.755281,
    "krw": 123.966225,
    "huf": 33.121225,
    "eur": 0.086815,
    "egp": 2.977135,
    "hrk": 0.649924,
    "mxn": 1.633233,
    "myr": 0.440332,
    "pln": 0.386482,
    "pkr": 27.663559,
    "nzd": 0.155472,
    "sek": 1,
    "ron": 0.427979,
    "sgd": 0.12834,
    "sar": 0.3626,
    "rub": 8.708656,
    "thb": 3.315615,
    "nok": 0.970351,
    "try": 2.595354,
    "twd": 3.014257,
    "usd": 0.096659,
    "zar": 1.733877,
    "vnd": 2286.33422,
    "php": 5.285,
    "omr": 0.037216,
    "npr": 12.765007,
    "lkr": 31.724843,
    "mad": 0.945944,
    "uah": 3.591097,
    "pab": 0.097236,
    "kwd": 0.029665,
    "kes": 13.708289,
    "jod": 0.068541,
    "ghs": 1.128399,
    "gel": 0.247935,
    "dzd": 13.03124,
    "isk": 12.700083
  }
}