{
  "date": "2023-06-28",
  "exchange-rates": {
    "chf": 0.500371,
    "ars": 142.842747,
    "aed": 2.055877,
    "bdt": 60.544476,
    "cop": 2332.039912,
    "czk": 12.078725,
    "bgn": 1,
    "brl": 2.693391,
    "aud": 0.843899,
    "clp": 446.476569,
    "cny": 4.04364,
    "cad": 0.739517,
    "egp": 17.296494,
    "dkk": 3.806411,
    "eur": 0.511163,
    "gbp": 0.439508,
    "hkd": 4.38459,
    "idr": 8397.414616,
    "jpy": 80.508689,
    "inr": 45.906475,
    "hrk": 3.904613,
    "ils": 2.055539,
    "huf": 189.351549,
    "krw": 729.861609,
    "nok": 6.058367,
    "myr": 2.611041,
    "mxn": 9.567952,
    "sar": 2.099214,
    "pln": 2.273556,
    "sek": 6.016772,
    "ron": 2.536727,
    "nzd": 0.912677,
    "rub": 47.785412,
    "pkr": 159.327082,
    "sgd": 0.755754,
    "thb": 19.7913,
    "twd": 17.369262,
    "try": 14.659403,
    "uah": 20.665541,
    "usd": 0.559712,
    "pab": 0.559513,
    "vnd": 13170.022589,
    "zar": 10.395361,
    "php": 30.920446,
    "npr": 73.42418,
    "mad": 5.545261,
    "omr": 0.215482,
    "lkr": 172.911958,
    "kwd": 0.171966,
    "kes": 78.611623,
    "jod": 0.397117,
    "isk": 76.00737,
    "dzd": 75.827922,
    "ghs": 6.435086,
    "gel": 1.474841
  }
}