{
  "date": "2023-07-05",
  "exchange-rates": {
    "brl": 0.087443,
    "bgn": 0.032441,
    "ars": 4.681549,
    "aed": 0.066343,
    "bdt": 1.958615,
    "cad": 0.023882,
    "cny": 0.130349,
    "chf": 0.016198,
    "aud": 0.026974,
    "czk": 0.393941,
    "cop": 75.101199,
    "clp": 14.437452,
    "dkk": 0.123594,
    "eur": 0.016593,
    "gbp": 0.01421,
    "egp": 0.558069,
    "hrk": 0.126002,
    "hkd": 0.141428,
    "huf": 6.232275,
    "ils": 0.066888,
    "idr": 271.074549,
    "jpy": 2.611369,
    "krw": 23.490285,
    "inr": 1.481796,
    "mxn": 0.308085,
    "myr": 0.083789,
    "nok": 0.192315,
    "nzd": 0.029135,
    "pkr": 4.971072,
    "pln": 0.073574,
    "ron": 0.082171,
    "rub": 1.643637,
    "sar": 0.067737,
    "sek": 0.195481,
    "sgd": 0.024377,
    "thb": 0.630388,
    "try": 0.469419,
    "uah": 0.667598,
    "twd": 0.562187,
    "usd": 0.018062,
    "vnd": 428.248678,
    "zar": 0.337026,
    "pab": 0.018076,
    "omr": 0.006954,
    "php": 1,
    "mad": 0.177065,
    "lkr": 5.531602,
    "npr": 2.37202,
    "kwd": 0.00555,
    "kes": 2.542218,
    "ghs": 0.205616,
    "jod": 0.012813,
    "isk": 2.477377,
    "gel": 0.047052,
    "dzd": 2.452523
  }
}