{
  "date": "2023-07-25",
  "exchange-rates": {
    "aed": 0.470032,
    "brl": 0.604953,
    "ars": 34.682632,
    "chf": 0.111203,
    "bdt": 13.921857,
    "czk": 2.78784,
    "cny": 0.919639,
    "clp": 106.033308,
    "cad": 0.168451,
    "aud": 0.189513,
    "cop": 505.541852,
    "bgn": 0.225965,
    "dkk": 0.861015,
    "hkd": 1,
    "egp": 3.953943,
    "hrk": 0.860472,
    "gbp": 0.099749,
    "huf": 43.648765,
    "eur": 0.115557,
    "idr": 1918.058839,
    "inr": 10.46863,
    "ils": 0.468762,
    "krw": 163.83419,
    "jpy": 18.090707,
    "nok": 1.285495,
    "mxn": 2.154896,
    "pkr": 36.921945,
    "myr": 0.583816,
    "rub": 11.568118,
    "ron": 0.568366,
    "pln": 0.514377,
    "nzd": 0.205981,
    "sar": 0.479968,
    "sek": 1.330458,
    "thb": 4.409307,
    "sgd": 0.170244,
    "try": 3.447527,
    "vnd": 3029.760009,
    "uah": 4.736632,
    "twd": 4.008754,
    "zar": 2.266196,
    "usd": 0.127973,
    "omr": 0.049273,
    "npr": 16.800195,
    "php": 6.973885,
    "pab": 0.128257,
    "lkr": 42.516973,
    "mad": 1.250747,
    "kes": 18.237421,
    "gel": 0.332091,
    "dzd": 17.264961,
    "ghs": 1.486424,
    "jod": 0.090731,
    "isk": 16.905186,
    "kwd": 0.039289
  }
}