{
  "date": "2023-08-10",
  "exchange-rates": {
    "ars": 285.10481,
    "czk": 22.115921,
    "chf": 0.87673,
    "aud": 1.529732,
    "clp": 861.673418,
    "bgn": 1.783159,
    "cny": 7.203755,
    "brl": 4.902079,
    "aed": 3.672146,
    "cad": 1.341439,
    "cop": 4052.795494,
    "bdt": 109.456965,
    "egp": 30.891256,
    "dkk": 6.787782,
    "huf": 354.303159,
    "eur": 0.911047,
    "gbp": 0.786181,
    "hrk": 6.722326,
    "krw": 1317.497203,
    "inr": 82.822456,
    "hkd": 7.817912,
    "ils": 3.688349,
    "idr": 15189.035143,
    "jpy": 143.766706,
    "pkr": 287.506237,
    "myr": 4.571456,
    "rub": 96.852929,
    "ron": 4.505869,
    "nok": 10.202272,
    "mxn": 17.060888,
    "sar": 3.751093,
    "sgd": 1.346288,
    "sek": 10.666832,
    "thb": 35.038021,
    "pln": 4.069232,
    "nzd": 1.650294,
    "try": 26.991246,
    "twd": 31.783692,
    "uah": 36.939028,
    "vnd": 23739.584628,
    "usd": 0.999772,
    "zar": 18.978086,
    "php": 56.398634,
    "pab": 1,
    "omr": 0.384863,
    "npr": 132.566329,
    "mad": 9.723393,
    "lkr": 319.068784,
    "kwd": 0.307621,
    "dzd": 135.788192,
    "kes": 142.201125,
    "isk": 131.459611,
    "ghs": 11.166178,
    "gel": 2.604403,
    "jod": 0.707938
  }
}