{
  "date": "2023-08-10",
  "exchange-rates": {
    "bgn": 0.438205,
    "cad": 0.329654,
    "chf": 0.215453,
    "bdt": 26.898677,
    "ars": 70.063537,
    "clp": 211.753312,
    "czk": 5.434912,
    "aud": 0.375926,
    "cny": 1.770298,
    "cop": 995.960711,
    "aed": 0.902417,
    "brl": 1.204669,
    "gbp": 0.193201,
    "eur": 0.223887,
    "hrk": 1.651989,
    "dkk": 1.668074,
    "egp": 7.591421,
    "hkd": 1.921225,
    "huf": 87.068797,
    "idr": 3732.653738,
    "ils": 0.906399,
    "krw": 323.770458,
    "inr": 20.353337,
    "jpy": 35.330179,
    "mxn": 4.192655,
    "nzd": 0.405554,
    "myr": 1.12342,
    "nok": 2.507174,
    "pln": 1,
    "pkr": 70.65368,
    "rub": 23.801278,
    "ron": 1.107302,
    "sar": 0.921818,
    "sgd": 0.330846,
    "thb": 8.610474,
    "sek": 2.621338,
    "twd": 7.810734,
    "usd": 0.245691,
    "uah": 9.077641,
    "try": 6.633007,
    "vnd": 5833.922198,
    "php": 13.859773,
    "zar": 4.6638,
    "pab": 0.245747,
    "omr": 0.094579,
    "npr": 32.577725,
    "lkr": 78.410069,
    "mad": 2.389491,
    "kwd": 0.075597,
    "jod": 0.173973,
    "kes": 34.945443,
    "ghs": 2.74405,
    "isk": 32.305752,
    "gel": 0.640023,
    "dzd": 33.369487
  }
}