{
  "date": "2023-08-05",
  "exchange-rates": {
    "cop": 572.394305,
    "aud": 0.211779,
    "clp": 118.803389,
    "bgn": 0.247613,
    "brl": 0.679627,
    "czk": 3.074106,
    "bdt": 15.204542,
    "ars": 38.891348,
    "cny": 1,
    "cad": 0.186641,
    "chf": 0.121691,
    "hkd": 1.089231,
    "huf": 49.367589,
    "dkk": 0.943846,
    "gbp": 0.109395,
    "ils": 0.509395,
    "jpy": 19.768637,
    "idr": 2113.167758,
    "inr": 11.530772,
    "hrk": 0.937685,
    "eur": 0.126493,
    "egp": 4.309594,
    "pkr": 39.540475,
    "nzd": 0.23117,
    "nok": 1.422163,
    "myr": 0.635229,
    "mxn": 2.381705,
    "pln": 0.561747,
    "krw": 181.85668,
    "ron": 0.626522,
    "sar": 0.52317,
    "aed": 0.512228,
    "rub": 13.370381,
    "sgd": 0.186747,
    "zar": 2.575613,
    "vnd": 3309.995891,
    "uah": 5.15221,
    "twd": 4.416094,
    "sek": 1.476411,
    "pab": 0.139504,
    "usd": 0.139456,
    "php": 7.745196,
    "thb": 4.836397,
    "try": 3.757052,
    "omr": 0.053689,
    "mad": 1.357881,
    "lkr": 44.780045,
    "kes": 19.836321,
    "jod": 0.09875,
    "ghs": 1.576281,
    "gel": 0.363289,
    "kwd": 0.042887,
    "isk": 18.377608,
    "npr": 18.479719,
    "dzd": 18.901846
  }
}