{
  "date": "2023-08-05",
  "exchange-rates": {
    "bgn": 0.681586,
    "brl": 1.870759,
    "aed": 1.409972,
    "cop": 1575.587809,
    "bdt": 41.852426,
    "czk": 8.461866,
    "aud": 0.582948,
    "chf": 0.334969,
    "clp": 327.021374,
    "ars": 107.053361,
    "cad": 0.513754,
    "cny": 2.752627,
    "hkd": 2.998245,
    "gbp": 0.301123,
    "dkk": 2.598056,
    "idr": 5816.76185,
    "egp": 11.862704,
    "eur": 0.348187,
    "hrk": 2.581096,
    "jpy": 54.415677,
    "huf": 135.890539,
    "inr": 31.73991,
    "krw": 500.583542,
    "ils": 1.402174,
    "mxn": 6.555946,
    "nzd": 0.636324,
    "ron": 1.724581,
    "myr": 1.748548,
    "rub": 36.803666,
    "pkr": 108.840166,
    "nok": 3.914684,
    "pln": 1.546279,
    "sar": 1.440091,
    "sek": 4.064007,
    "thb": 13.312795,
    "sgd": 0.514044,
    "usd": 0.383871,
    "zar": 7.089702,
    "twd": 12.155859,
    "try": 10.34176,
    "npr": 50.867766,
    "pab": 0.384001,
    "php": 21.319632,
    "vnd": 9111.182844,
    "omr": 0.147787,
    "uah": 14.18211,
    "mad": 3.737739,
    "jod": 0.271821,
    "kes": 54.601987,
    "gel": 1,
    "lkr": 123.262745,
    "kwd": 0.118052,
    "dzd": 52.029725,
    "ghs": 4.338913,
    "isk": 50.586694
  }
}