{
  "date": "2023-08-05",
  "exchange-rates": {
    "cop": 913.606021,
    "aud": 0.338023,
    "cad": 0.297901,
    "ars": 62.074989,
    "bdt": 24.268167,
    "aed": 0.817574,
    "czk": 4.906621,
    "clp": 189.62364,
    "bgn": 0.395218,
    "cny": 1.596113,
    "chf": 0.194232,
    "brl": 1.084762,
    "hrk": 1.496651,
    "eur": 0.201896,
    "gbp": 0.174606,
    "inr": 18.404416,
    "egp": 6.8786,
    "ils": 0.813052,
    "krw": 290.263821,
    "dkk": 1.506485,
    "huf": 78.796252,
    "idr": 3372.854638,
    "hkd": 1.738535,
    "jpy": 31.55298,
    "mxn": 3.801471,
    "pkr": 63.111069,
    "myr": 1.013897,
    "sgd": 0.298069,
    "sek": 2.356518,
    "ron": 1,
    "rub": 21.340639,
    "sar": 0.835038,
    "pln": 0.896611,
    "nok": 2.269933,
    "nzd": 0.368973,
    "thb": 7.719436,
    "try": 5.996679,
    "mad": 2.167331,
    "twd": 7.048586,
    "pab": 0.222663,
    "zar": 4.11097,
    "npr": 29.495721,
    "usd": 0.222588,
    "php": 12.362208,
    "uah": 8.223509,
    "omr": 0.085694,
    "lkr": 71.474015,
    "vnd": 5283.127641,
    "ghs": 2.515923,
    "kwd": 0.068453,
    "jod": 0.157615,
    "gel": 0.579851,
    "dzd": 30.169483,
    "isk": 29.332741,
    "kes": 31.661012
  }
}