{
  "date": "2023-07-21",
  "exchange-rates": {
    "bdt": 0.826801,
    "bgn": 0.013303,
    "chf": 0.006563,
    "czk": 0.163033,
    "clp": 6.186499,
    "brl": 0.036335,
    "cny": 0.054347,
    "cad": 0.009978,
    "aud": 0.011197,
    "aed": 0.027814,
    "ars": 2.034234,
    "cop": 30.129864,
    "hkd": 0.059168,
    "eur": 0.006801,
    "jpy": 1.060643,
    "ils": 0.027356,
    "inr": 0.6216,
    "hrk": 0.050915,
    "dkk": 0.050672,
    "idr": 113.771093,
    "huf": 2.594689,
    "egp": 0.233226,
    "krw": 9.71141,
    "gbp": 0.005884,
    "nzd": 0.01218,
    "myr": 0.034495,
    "sgd": 0.010054,
    "pkr": 2.16714,
    "mxn": 0.127946,
    "nok": 0.076016,
    "rub": 0.682229,
    "pln": 0.030277,
    "sar": 0.028406,
    "sek": 0.078339,
    "ron": 0.033528,
    "thb": 0.259743,
    "usd": 0.007572,
    "try": 0.203318,
    "vnd": 179.109509,
    "zar": 0.13583,
    "php": 0.414022,
    "pab": 0.007617,
    "npr": 1,
    "mad": 0.074104,
    "omr": 0.002915,
    "uah": 0.281324,
    "twd": 0.236134,
    "lkr": 2.485298,
    "isk": 0.994914,
    "jod": 0.005369,
    "ghs": 0.088398,
    "kwd": 0.002324,
    "dzd": 1.020856,
    "kes": 1.073896,
    "gel": 0.019423
  }
}