{
  "date": "2023-07-31",
  "exchange-rates": {
    "aed": 0.777313,
    "bgn": 0.375024,
    "chf": 0.184203,
    "cad": 0.280433,
    "bdt": 22.90456,
    "aud": 0.317403,
    "brl": 1,
    "clp": 175.28545,
    "cny": 1.505213,
    "czk": 4.604564,
    "ars": 57.64161,
    "cop": 831.264984,
    "egp": 6.523734,
    "dkk": 1.431116,
    "gbp": 0.164642,
    "huf": 73.964498,
    "hrk": 1.422926,
    "hkd": 1.650096,
    "eur": 0.19204,
    "ils": 0.783674,
    "inr": 17.39989,
    "jpy": 29.910621,
    "idr": 3193.724369,
    "krw": 269.503389,
    "mxn": 3.531888,
    "myr": 0.962993,
    "nzd": 0.342818,
    "nok": 2.158074,
    "pkr": 60.452545,
    "pln": 0.847146,
    "ron": 0.947587,
    "rub": 19.482105,
    "sar": 0.793842,
    "sek": 2.231167,
    "sgd": 0.28175,
    "thb": 7.241712,
    "try": 5.70035,
    "twd": 6.645502,
    "zar": 3.723787,
    "vnd": 5014.41528,
    "usd": 0.211623,
    "uah": 7.794643,
    "php": 11.606477,
    "pab": 0.211055,
    "omr": 0.081471,
    "npr": 27.765666,
    "mad": 2.055507,
    "lkr": 69.657013,
    "jod": 0.14985,
    "kes": 30.014613,
    "kwd": 0.064964,
    "isk": 27.826398,
    "ghs": 2.404104,
    "dzd": 28.731894,
    "gel": 0.548101
  }
}