{
  "date": "2023-07-08",
  "exchange-rates": {
    "aed": 0.040246,
    "cop": 45.98074,
    "cad": 0.014567,
    "chf": 0.009738,
    "clp": 8.726998,
    "bdt": 1.181161,
    "czk": 0.238158,
    "brl": 0.053496,
    "aud": 0.016382,
    "bgn": 0.019523,
    "cny": 0.079127,
    "ars": 2.857461,
    "egp": 0.338327,
    "dkk": 0.074422,
    "huf": 3.842893,
    "hkd": 0.085781,
    "ils": 0.040518,
    "krw": 14.227099,
    "gbp": 0.008535,
    "eur": 0.009985,
    "idr": 166.13673,
    "jpy": 1.557248,
    "hrk": 0.076442,
    "inr": 0.905272,
    "mxn": 0.187892,
    "myr": 0.051176,
    "pkr": 2.984588,
    "nok": 0.116942,
    "pln": 0.044491,
    "nzd": 0.017641,
    "rub": 1,
    "ron": 0.049421,
    "sar": 0.041102,
    "thb": 0.385074,
    "sek": 0.118574,
    "sgd": 0.014792,
    "try": 0.285559,
    "twd": 0.342737,
    "php": 0.608501,
    "vnd": 259.148622,
    "pab": 0.010872,
    "lkr": 3.392457,
    "mad": 0.106546,
    "uah": 0.401566,
    "npr": 1.439773,
    "zar": 0.209429,
    "omr": 0.004215,
    "usd": 0.010958,
    "kes": 1.51346,
    "kwd": 0.003363,
    "gel": 0.028436,
    "jod": 0.007773,
    "ghs": 0.123676,
    "dzd": 1.486309,
    "isk": 1.469755
  }
}