{
  "date": "2023-06-25",
  "exchange-rates": {
    "ars": 25.457471,
    "bdt": 10.861271,
    "cad": 0.133488,
    "bgn": 0.181358,
    "clp": 80.775446,
    "cny": 0.72534,
    "aed": 0.37105,
    "chf": 0.090583,
    "aud": 0.151278,
    "cop": 411.641878,
    "czk": 2.193131,
    "brl": 0.483207,
    "inr": 8.282469,
    "gbp": 0.079459,
    "dkk": 0.690557,
    "idr": 1519.930085,
    "hrk": 0.704752,
    "egp": 3.108908,
    "eur": 0.092417,
    "hkd": 0.79101,
    "krw": 132.206029,
    "jpy": 14.518138,
    "ils": 0.366617,
    "huf": 34.324821,
    "sgd": 0.136569,
    "ron": 0.459597,
    "nok": 1.09353,
    "sek": 1.073635,
    "sar": 0.378866,
    "pln": 0.411541,
    "pkr": 28.764602,
    "mxn": 1.733858,
    "rub": 8.549124,
    "thb": 3.561119,
    "myr": 0.472437,
    "nzd": 0.164467,
    "try": 2.553604,
    "php": 5.633584,
    "twd": 3.132085,
    "mad": 1,
    "vnd": 2376.579746,
    "pab": 0.1004,
    "omr": 0.038737,
    "usd": 0.101024,
    "npr": 13.168494,
    "lkr": 30.924643,
    "uah": 3.707927,
    "zar": 1.893715,
    "kes": 13.975444,
    "dzd": 13.656175,
    "kwd": 0.031067,
    "gel": 0.265191,
    "ghs": 1.158646,
    "isk": 13.810973,
    "jod": 0.071677
  }
}