{
  "date": "2023-06-25",
  "exchange-rates": {
    "chf": 0.550767,
    "ars": 154.788114,
    "czk": 13.334815,
    "cop": 2502.890766,
    "cny": 4.410255,
    "clp": 491.135932,
    "bdt": 66.039379,
    "aud": 0.919811,
    "bgn": 1.102704,
    "cad": 0.811639,
    "brl": 2.938025,
    "aed": 2.256081,
    "dkk": 4.198769,
    "eur": 0.561918,
    "egp": 18.902979,
    "gbp": 0.483129,
    "hkd": 4.809546,
    "jpy": 88.274092,
    "ils": 2.229128,
    "idr": 9241.574251,
    "huf": 208.703932,
    "krw": 803.84739,
    "hrk": 4.285076,
    "inr": 50.359589,
    "nok": 6.648951,
    "nzd": 1,
    "mxn": 10.542312,
    "sar": 2.303604,
    "sgd": 0.830374,
    "thb": 21.652536,
    "myr": 2.872542,
    "rub": 51.980923,
    "pln": 2.502277,
    "ron": 2.794471,
    "pkr": 174.896338,
    "try": 15.526582,
    "sek": 6.527981,
    "uah": 22.545171,
    "usd": 0.61425,
    "vnd": 14450.229259,
    "omr": 0.235533,
    "php": 34.25367,
    "npr": 80.067902,
    "twd": 19.0439,
    "mad": 6.080263,
    "pab": 0.610459,
    "lkr": 188.029957,
    "kwd": 0.188894,
    "jod": 0.435813,
    "kes": 84.974374,
    "zar": 11.514287,
    "isk": 83.974343,
    "ghs": 7.044874,
    "gel": 1.612431,
    "dzd": 83.03313
  }
}