{
  "date": "2023-08-19",
  "exchange-rates": {
    "clp": 483.696159,
    "brl": 2.75983,
    "aud": 0.870712,
    "ars": 193.983253,
    "cny": 4.043212,
    "cad": 0.75341,
    "czk": 12.266448,
    "bgn": 1,
    "aed": 2.039209,
    "cop": 2286.932124,
    "chf": 0.48977,
    "bdt": 60.762795,
    "ils": 2.107255,
    "dkk": 3.805392,
    "eur": 0.509957,
    "huf": 195.253214,
    "hkd": 4.349077,
    "gbp": 0.436048,
    "egp": 17.125162,
    "hrk": 3.821771,
    "inr": 46.174102,
    "idr": 8507.198267,
    "krw": 744.142686,
    "jpy": 80.743722,
    "sar": 2.082314,
    "pln": 2.277644,
    "pkr": 163.803041,
    "mxn": 9.47175,
    "rub": 52.25091,
    "ron": 2.525842,
    "sek": 6.088271,
    "nzd": 0.937629,
    "sgd": 0.754409,
    "nok": 5.921614,
    "myr": 2.583367,
    "thb": 19.751017,
    "pab": 0.555154,
    "mad": 5.512127,
    "try": 15.050874,
    "twd": 17.719048,
    "uah": 20.503621,
    "usd": 0.555264,
    "php": 31.212516,
    "npr": 73.841175,
    "omr": 0.213775,
    "zar": 10.584452,
    "vnd": 13226.386183,
    "lkr": 179.326366,
    "gel": 1.455008,
    "kwd": 0.171016,
    "isk": 73.408007,
    "dzd": 75.462521,
    "jod": 0.393018,
    "kes": 80.071167,
    "ghs": 6.266175
  }
}