{
  "date": "2023-08-19",
  "exchange-rates": {
    "bgn": 1.06652,
    "brl": 2.943413,
    "cny": 4.312165,
    "cop": 2439.058021,
    "czk": 13.082408,
    "ars": 206.886949,
    "clp": 515.871452,
    "cad": 0.803527,
    "bdt": 64.804714,
    "aed": 2.174856,
    "chf": 0.522349,
    "aud": 0.928631,
    "dkk": 4.058526,
    "ils": 2.247428,
    "egp": 18.264321,
    "krw": 793.642788,
    "gbp": 0.465054,
    "eur": 0.543879,
    "jpy": 86.114765,
    "hkd": 4.638376,
    "huf": 208.241388,
    "hrk": 4.075993,
    "inr": 49.245587,
    "idr": 9073.094017,
    "mxn": 10.101808,
    "nzd": 1,
    "nok": 6.315518,
    "sar": 2.220829,
    "myr": 2.755212,
    "ron": 2.69386,
    "pkr": 174.699161,
    "pln": 2.429152,
    "sek": 6.493261,
    "thb": 21.064847,
    "rub": 55.726622,
    "sgd": 0.804593,
    "try": 16.052053,
    "zar": 11.288526,
    "twd": 18.897712,
    "php": 33.288761,
    "mad": 5.878791,
    "usd": 0.5922,
    "npr": 78.753063,
    "lkr": 191.255091,
    "uah": 21.867515,
    "vnd": 14106.200605,
    "omr": 0.227995,
    "pab": 0.592083,
    "kwd": 0.182392,
    "dzd": 80.482261,
    "isk": 78.291081,
    "jod": 0.419161,
    "ghs": 6.682999,
    "kes": 85.397472,
    "gel": 1.551795
  }
}