{
  "date": "2023-07-01",
  "exchange-rates": {
    "bgn": 0.18112,
    "brl": 0.483963,
    "chf": 0.090405,
    "cny": 0.732917,
    "cop": 421.136061,
    "ars": 25.912266,
    "clp": 80.980827,
    "czk": 2.200214,
    "cad": 0.133833,
    "aud": 0.151646,
    "bdt": 10.931154,
    "aed": 0.371124,
    "hkd": 0.791818,
    "inr": 8.295032,
    "jpy": 14.580628,
    "krw": 132.999759,
    "huf": 34.525865,
    "idr": 1519.676751,
    "eur": 0.092558,
    "hrk": 0.704869,
    "gbp": 0.079683,
    "egp": 3.118852,
    "ils": 0.374795,
    "dkk": 0.689545,
    "nok": 1.092472,
    "myr": 0.471606,
    "mxn": 1.730245,
    "pkr": 28.948426,
    "sek": 1.089943,
    "thb": 3.563729,
    "sar": 0.378983,
    "sgd": 0.136627,
    "rub": 8.975011,
    "ron": 0.459232,
    "nzd": 0.165367,
    "pln": 0.410636,
    "try": 2.632212,
    "vnd": 2383.035989,
    "twd": 3.148548,
    "php": 5.584907,
    "npr": 13.259674,
    "uah": 3.73188,
    "omr": 0.038902,
    "zar": 1.903171,
    "usd": 0.10104,
    "lkr": 31.123849,
    "pab": 0.101044,
    "mad": 1,
    "kwd": 0.031068,
    "ghs": 1.156951,
    "jod": 0.071689,
    "kes": 14.206654,
    "dzd": 13.722189,
    "isk": 13.768804,
    "gel": 0.263755
  }
}