{
  "date": "2023-07-01",
  "exchange-rates": {
    "brl": 0.086656,
    "cny": 0.131232,
    "aud": 0.027153,
    "bgn": 0.03243,
    "bdt": 1.957267,
    "chf": 0.016187,
    "clp": 14.499943,
    "cop": 75.406105,
    "ars": 4.639695,
    "aed": 0.066451,
    "cad": 0.023963,
    "czk": 0.393957,
    "dkk": 0.123466,
    "hrk": 0.12621,
    "jpy": 2.61072,
    "hkd": 0.141778,
    "inr": 1.485259,
    "egp": 0.558443,
    "krw": 23.814142,
    "eur": 0.016573,
    "idr": 272.104234,
    "gbp": 0.014268,
    "ils": 0.067109,
    "huf": 6.181995,
    "myr": 0.084443,
    "mxn": 0.309807,
    "pkr": 5.183332,
    "ron": 0.082227,
    "nzd": 0.02961,
    "nok": 0.195612,
    "rub": 1.607012,
    "pln": 0.073526,
    "sar": 0.067858,
    "sek": 0.195159,
    "sgd": 0.024464,
    "thb": 0.6381,
    "try": 0.471308,
    "twd": 0.56376,
    "usd": 0.018092,
    "vnd": 426.692177,
    "npr": 2.374198,
    "omr": 0.006965,
    "pab": 0.018092,
    "mad": 0.179054,
    "uah": 0.668208,
    "zar": 0.34077,
    "php": 1,
    "lkr": 5.57285,
    "kwd": 0.005563,
    "jod": 0.012836,
    "kes": 2.543758,
    "ghs": 0.207157,
    "isk": 2.46536,
    "dzd": 2.457013,
    "gel": 0.047226
  }
}