{
  "date": "2023-07-03",
  "exchange-rates": {
    "aed": 0.066565,
    "ars": 4.616599,
    "aud": 0.027195,
    "cny": 0.131431,
    "brl": 0.086737,
    "cad": 0.024,
    "bdt": 1.951871,
    "clp": 14.529494,
    "cop": 75.662153,
    "czk": 0.394277,
    "bgn": 0.032481,
    "chf": 0.016218,
    "dkk": 0.123627,
    "gbp": 0.014264,
    "eur": 0.0166,
    "egp": 0.556738,
    "hrk": 0.126426,
    "hkd": 0.142015,
    "idr": 272.174434,
    "jpy": 2.617312,
    "ils": 0.067249,
    "huf": 6.188385,
    "krw": 23.774135,
    "inr": 1.486628,
    "mxn": 0.310257,
    "myr": 0.084579,
    "nzd": 0.029504,
    "nok": 0.194563,
    "pln": 0.073663,
    "pkr": 5.170353,
    "ron": 0.082329,
    "rub": 1.59389,
    "sek": 0.195279,
    "sar": 0.06798,
    "sgd": 0.024487,
    "thb": 0.638217,
    "try": 0.47235,
    "uah": 0.666366,
    "usd": 0.018123,
    "zar": 0.341579,
    "vnd": 426.725482,
    "php": 1,
    "pab": 0.018042,
    "omr": 0.006982,
    "twd": 0.563298,
    "npr": 2.367608,
    "mad": 0.178126,
    "lkr": 5.557587,
    "kwd": 0.005572,
    "jod": 0.012858,
    "ghs": 0.205688,
    "isk": 2.468484,
    "kes": 2.548005,
    "dzd": 2.466223,
    "gel": 0.047295
  }
}