{
  "date": "2023-07-03",
  "exchange-rates": {
    "czk": 0.591682,
    "chf": 0.024339,
    "cad": 0.036016,
    "aud": 0.040811,
    "brl": 0.130164,
    "cop": 113.54449,
    "cny": 0.197236,
    "bdt": 2.929128,
    "aed": 0.099892,
    "ars": 6.928026,
    "bgn": 0.048743,
    "clp": 21.804084,
    "dkk": 0.185524,
    "egp": 0.835484,
    "gbp": 0.021406,
    "hkd": 0.213119,
    "eur": 0.024911,
    "hrk": 0.189724,
    "idr": 408.446047,
    "huf": 9.28677,
    "ils": 0.100919,
    "inr": 2.230949,
    "krw": 35.67731,
    "jpy": 3.927742,
    "mxn": 0.465596,
    "myr": 0.126925,
    "nok": 0.291977,
    "pln": 0.110545,
    "sek": 0.29305,
    "thb": 0.957758,
    "sgd": 0.036748,
    "nzd": 0.044277,
    "sar": 0.102016,
    "rub": 2.391915,
    "pkr": 7.759033,
    "ron": 0.12355,
    "twd": 0.845329,
    "try": 0.708846,
    "usd": 0.027196,
    "vnd": 640.377326,
    "uah": 1,
    "pab": 0.027075,
    "php": 1.500677,
    "zar": 0.5126,
    "omr": 0.010478,
    "lkr": 8.340146,
    "mad": 0.267309,
    "npr": 3.553017,
    "kes": 3.823733,
    "kwd": 0.008362,
    "jod": 0.019296,
    "isk": 3.704398,
    "ghs": 0.308671,
    "dzd": 3.701006,
    "gel": 0.070975
  }
}