{
  "date": "2023-07-30",
  "exchange-rates": {
    "clp": 624.162268,
    "cop": 2973.894523,
    "bdt": 81.578665,
    "cad": 1,
    "czk": 16.429488,
    "aud": 1.13504,
    "aed": 2.772048,
    "brl": 3.570734,
    "chf": 0.656695,
    "ars": 206.148057,
    "bgn": 1.338895,
    "cny": 5.39474,
    "dkk": 5.104864,
    "huf": 263.326076,
    "egp": 23.275563,
    "hrk": 5.074417,
    "hkd": 5.886379,
    "gbp": 0.587489,
    "jpy": 106.520487,
    "ils": 2.794688,
    "idr": 11401.45097,
    "eur": 0.684128,
    "inr": 62.080458,
    "krw": 961.005065,
    "pkr": 215.319332,
    "mxn": 12.595446,
    "nzd": 1.224348,
    "myr": 3.436476,
    "nok": 7.69586,
    "ron": 3.378767,
    "rub": 69.476871,
    "pln": 3.022788,
    "sar": 2.831001,
    "sek": 7.959254,
    "sgd": 1.004417,
    "thb": 25.602069,
    "try": 20.316887,
    "twd": 23.644231,
    "zar": 13.034559,
    "php": 41.445237,
    "usd": 0.754688,
    "uah": 27.763141,
    "pab": 0.751714,
    "npr": 98.895498,
    "vnd": 17882.335312,
    "mad": 7.321087,
    "omr": 0.290584,
    "lkr": 248.100347,
    "kes": 106.900191,
    "jod": 0.534398,
    "isk": 99.264422,
    "gel": 1.954937,
    "kwd": 0.231674,
    "ghs": 8.562683,
    "dzd": 102.463284
  }
}