{
  "date": "2023-07-15",
  "exchange-rates": {
    "cad": 0.042881,
    "cop": 132.520606,
    "aed": 0.119076,
    "bdt": 3.517494,
    "clp": 26.239264,
    "aud": 0.047402,
    "cny": 0.231509,
    "brl": 0.15511,
    "chf": 0.027987,
    "bgn": 0.056372,
    "ars": 8.549253,
    "czk": 0.686199,
    "hkd": 0.253318,
    "dkk": 0.215057,
    "eur": 0.028825,
    "idr": 486.371677,
    "jpy": 4.497878,
    "egp": 1,
    "inr": 2.660813,
    "huf": 10.806651,
    "hrk": 0.217976,
    "gbp": 0.024765,
    "ils": 0.116917,
    "krw": 41.148878,
    "mxn": 0.542872,
    "pln": 0.128365,
    "pkr": 8.860505,
    "sgd": 0.042821,
    "ron": 0.142504,
    "thb": 1.122258,
    "myr": 0.146726,
    "sek": 0.331688,
    "nzd": 0.050888,
    "rub": 2.925763,
    "sar": 0.121402,
    "nok": 0.32581,
    "try": 0.848397,
    "uah": 1.188244,
    "zar": 0.586937,
    "pab": 0.032336,
    "php": 1.761946,
    "mad": 0.311453,
    "npr": 4.248948,
    "vnd": 766.449535,
    "usd": 0.032418,
    "twd": 0.999926,
    "lkr": 10.364574,
    "omr": 0.012459,
    "kwd": 0.009928,
    "kes": 4.598536,
    "dzd": 4.350222,
    "gel": 0.083478,
    "isk": 4.241622,
    "ghs": 0.367831,
    "jod": 0.022994
  }
}