{
  "date": "2023-07-15",
  "exchange-rates": {
    "brl": 0.612313,
    "ars": 33.749117,
    "clp": 103.582377,
    "cop": 523.139642,
    "bgn": 0.222535,
    "chf": 0.11048,
    "czk": 2.708847,
    "cny": 0.913907,
    "cad": 0.169279,
    "aed": 0.470065,
    "aud": 0.187125,
    "bdt": 13.885693,
    "egp": 3.94761,
    "hrk": 0.860484,
    "krw": 162.439715,
    "jpy": 17.755866,
    "dkk": 0.84896,
    "gbp": 0.097762,
    "inr": 10.50385,
    "ils": 0.461544,
    "eur": 0.113789,
    "huf": 42.660442,
    "idr": 1920.0056,
    "hkd": 1,
    "pkr": 34.977816,
    "ron": 0.562552,
    "sek": 1.309374,
    "pln": 0.506734,
    "myr": 0.579219,
    "thb": 4.430236,
    "mxn": 2.143047,
    "sgd": 0.169042,
    "nok": 1.286173,
    "rub": 11.549772,
    "sar": 0.479247,
    "nzd": 0.200887,
    "try": 3.349139,
    "vnd": 3025.643698,
    "twd": 3.947319,
    "lkr": 40.915295,
    "uah": 4.690725,
    "omr": 0.049185,
    "npr": 16.773189,
    "zar": 2.316997,
    "php": 6.955477,
    "mad": 1.229495,
    "usd": 0.127975,
    "pab": 0.127651,
    "kwd": 0.039194,
    "jod": 0.090773,
    "gel": 0.32954,
    "ghs": 1.452053,
    "isk": 16.744269,
    "dzd": 17.172979,
    "kes": 18.153225
  }
}