{
  "date": "2023-07-11",
  "exchange-rates": {
    "aed": 0.979162,
    "ars": 69.984207,
    "aud": 0.398409,
    "chf": 0.235803,
    "bgn": 0.473601,
    "cop": 1108.958847,
    "bdt": 28.823614,
    "cny": 1.927936,
    "czk": 5.769523,
    "clp": 216.697434,
    "brl": 1.306199,
    "cad": 0.353681,
    "dkk": 1.804025,
    "gbp": 0.207078,
    "egp": 8.236445,
    "hkd": 2.08727,
    "hrk": 1.859669,
    "idr": 4052.231595,
    "inr": 22.026028,
    "huf": 92.16099,
    "ils": 0.986347,
    "eur": 0.242086,
    "jpy": 37.607566,
    "krw": 345.515368,
    "myr": 1.242913,
    "mxn": 4.545904,
    "pkr": 73.272939,
    "ron": 1.197941,
    "sar": 1,
    "nzd": 0.428521,
    "nok": 2.787196,
    "pln": 1.07469,
    "sek": 2.863794,
    "rub": 24.072083,
    "sgd": 0.35815,
    "thb": 9.316334,
    "try": 6.958583,
    "uah": 9.8035,
    "twd": 8.36131,
    "pab": 0.265421,
    "omr": 0.102631,
    "php": 14.796343,
    "zar": 5.000499,
    "vnd": 6305.204119,
    "usd": 0.266577,
    "mad": 2.609141,
    "npr": 35.083382,
    "lkr": 83.084956,
    "kwd": 0.08181,
    "ghs": 3.019202,
    "gel": 0.690478,
    "isk": 35.606679,
    "kes": 37.614555,
    "dzd": 36.061323,
    "jod": 0.189109
  }
}