{
  "date": "2023-07-24",
  "exchange-rates": {
    "ars": 0.787172,
    "bdt": 0.317979,
    "bgn": 0.005148,
    "cny": 0.021057,
    "brl": 0.013999,
    "cop": 11.643689,
    "aud": 0.004359,
    "chf": 0.002539,
    "clp": 2.40193,
    "czk": 0.0633,
    "cad": 0.003874,
    "aed": 0.01076,
    "dkk": 0.019625,
    "egp": 0.09025,
    "eur": 0.002634,
    "hkd": 0.022904,
    "gbp": 0.002279,
    "huf": 1,
    "ils": 0.010606,
    "hrk": 0.019698,
    "krw": 3.773649,
    "inr": 0.2403,
    "idr": 44.005719,
    "jpy": 0.415172,
    "mxn": 0.049797,
    "myr": 0.013402,
    "nzd": 0.004753,
    "nok": 0.029541,
    "pkr": 0.840051,
    "sgd": 0.0039,
    "rub": 0.265113,
    "thb": 0.101246,
    "sek": 0.030486,
    "pln": 0.011754,
    "ron": 0.012999,
    "sar": 0.010989,
    "try": 0.078972,
    "twd": 0.091884,
    "vnd": 69.307323,
    "uah": 0.107665,
    "usd": 0.00293,
    "omr": 0.001128,
    "php": 0.160458,
    "pab": 0.00293,
    "zar": 0.052751,
    "mad": 0.028387,
    "npr": 0.384333,
    "lkr": 0.961652,
    "kwd": 0.0009,
    "kes": 0.416561,
    "jod": 0.002077,
    "isk": 0.385361,
    "ghs": 0.033983,
    "dzd": 0.394718,
    "gel": 0.00756
  }
}