{
  "date": "2023-07-24",
  "exchange-rates": {
    "bdt": 6.385475,
    "bgn": 0.103389,
    "aed": 0.21608,
    "ars": 15.80756,
    "aud": 0.087538,
    "cop": 233.822099,
    "cny": 0.422865,
    "cad": 0.077788,
    "czk": 1.271147,
    "clp": 48.234225,
    "brl": 0.281111,
    "chf": 0.050978,
    "gbp": 0.045771,
    "dkk": 0.3941,
    "egp": 1.81235,
    "eur": 0.05289,
    "hrk": 0.39557,
    "jpy": 8.337246,
    "idr": 883.698435,
    "hkd": 0.459949,
    "krw": 75.780332,
    "inr": 4.825572,
    "ils": 0.21298,
    "huf": 20.081445,
    "nzd": 0.095453,
    "pkr": 16.869447,
    "myr": 0.269122,
    "mxn": 1,
    "sgd": 0.078319,
    "ron": 0.261032,
    "sar": 0.220683,
    "sek": 0.612197,
    "thb": 2.033165,
    "pln": 0.236038,
    "nok": 0.593228,
    "rub": 5.323846,
    "try": 1.585868,
    "usd": 0.058831,
    "uah": 2.16206,
    "pab": 0.058831,
    "mad": 0.570055,
    "vnd": 1391.791207,
    "twd": 1.845169,
    "php": 3.222224,
    "zar": 1.059315,
    "omr": 0.022649,
    "npr": 7.717964,
    "lkr": 19.311355,
    "kwd": 0.018066,
    "kes": 8.365156,
    "jod": 0.041717,
    "dzd": 7.9265,
    "gel": 0.151811,
    "isk": 7.738608,
    "ghs": 0.682436
  }
}