{
  "date": "2023-08-03",
  "exchange-rates": {
    "ars": 8.760923,
    "aud": 0.048282,
    "aed": 0.116017,
    "brl": 0.151994,
    "cny": 0.225778,
    "cad": 0.04214,
    "bdt": 3.469709,
    "chf": 0.027701,
    "czk": 0.691788,
    "clp": 26.687184,
    "bgn": 0.056461,
    "cop": 127.713342,
    "egp": 0.976038,
    "idr": 479.484113,
    "hkd": 0.246479,
    "dkk": 0.215013,
    "hrk": 0.212384,
    "huf": 11.211343,
    "inr": 2.613046,
    "eur": 0.028854,
    "ils": 0.116002,
    "gbp": 0.024823,
    "jpy": 4.525708,
    "krw": 40.929402,
    "pkr": 9.034267,
    "nzd": 0.051929,
    "mxn": 0.537097,
    "nok": 0.324486,
    "pln": 0.128279,
    "myr": 0.143924,
    "ron": 0.142421,
    "sek": 0.33772,
    "sar": 0.118513,
    "rub": 2.970723,
    "sgd": 0.042374,
    "thb": 1.087541,
    "vnd": 749.786175,
    "zar": 0.582393,
    "uah": 1.170803,
    "try": 0.851655,
    "usd": 0.031587,
    "npr": 4.189176,
    "twd": 1,
    "omr": 0.012161,
    "php": 1.746799,
    "pab": 0.0317,
    "mad": 0.313989,
    "lkr": 9.985708,
    "isk": 4.175103,
    "jod": 0.022373,
    "ghs": 0.356671,
    "kwd": 0.009724,
    "gel": 0.083963,
    "dzd": 4.288981,
    "kes": 4.50771
  }
}