{
  "date": "2023-06-22",
  "exchange-rates": {
    "clp": 450.951931,
    "cad": 0.739181,
    "brl": 2.676688,
    "chf": 0.501377,
    "cop": 2334.267555,
    "cny": 4.034152,
    "ars": 141.527161,
    "bdt": 60.405961,
    "bgn": 1,
    "czk": 12.133921,
    "aud": 0.826273,
    "aed": 2.063796,
    "gbp": 0.439995,
    "dkk": 3.80709,
    "egp": 17.361771,
    "eur": 0.511161,
    "ils": 2.035371,
    "inr": 46.042286,
    "hrk": 3.919868,
    "jpy": 79.692122,
    "krw": 725.104945,
    "huf": 188.983489,
    "hkd": 4.397843,
    "idr": 8386.92766,
    "nok": 5.97952,
    "mxn": 9.627025,
    "nzd": 0.904255,
    "pln": 2.267426,
    "pkr": 160.166382,
    "sek": 5.983684,
    "ron": 2.536976,
    "sar": 2.107871,
    "sgd": 0.753211,
    "myr": 2.610862,
    "thb": 19.558563,
    "rub": 47.002914,
    "try": 13.245129,
    "uah": 20.619587,
    "twd": 17.372896,
    "usd": 0.561899,
    "vnd": 13210.237758,
    "php": 31.224429,
    "pab": 0.558345,
    "zar": 10.305165,
    "npr": 73.245999,
    "omr": 0.216319,
    "mad": 5.571175,
    "lkr": 171.973428,
    "kwd": 0.172626,
    "kes": 78.831619,
    "jod": 0.398611,
    "dzd": 76.127718,
    "isk": 75.603532,
    "ghs": 6.322862,
    "gel": 1.469342
  }
}