{
  "date": "2023-07-15",
  "exchange-rates": {
    "aed": 2.776868,
    "brl": 3.617187,
    "bdt": 82.028567,
    "cny": 5.398828,
    "ars": 199.370079,
    "chf": 0.652653,
    "clp": 611.904208,
    "czk": 16.002288,
    "cop": 3090.403572,
    "bgn": 1.314607,
    "aud": 1.105426,
    "cad": 1,
    "dkk": 5.015158,
    "gbp": 0.577518,
    "eur": 0.672198,
    "huf": 252.012984,
    "hkd": 5.907416,
    "ils": 2.726534,
    "krw": 959.598998,
    "idr": 11342.272106,
    "egp": 23.320174,
    "jpy": 104.891288,
    "hrk": 5.083239,
    "inr": 62.050616,
    "nok": 7.597957,
    "myr": 3.421687,
    "thb": 26.171246,
    "mxn": 12.659871,
    "sgd": 0.998604,
    "pln": 2.993488,
    "ron": 3.323229,
    "sar": 2.831112,
    "pkr": 206.628515,
    "sek": 7.73502,
    "rub": 68.229307,
    "nzd": 1.18672,
    "uah": 27.710063,
    "twd": 23.318453,
    "try": 19.784757,
    "vnd": 17873.736471,
    "usd": 0.756,
    "php": 41.088898,
    "zar": 13.687464,
    "npr": 99.086207,
    "pab": 0.754085,
    "omr": 0.290558,
    "lkr": 241.703675,
    "mad": 7.263141,
    "kwd": 0.231533,
    "jod": 0.536234,
    "dzd": 101.447931,
    "ghs": 8.577883,
    "gel": 1.946731,
    "kes": 107.238657,
    "isk": 98.915368
  }
}